MANIFEST.in
README.md
setup.py
pyokt/__init__.py
pyokt/util.py
pyokt.egg-info/PKG-INFO
pyokt.egg-info/SOURCES.txt
pyokt.egg-info/dependency_links.txt
pyokt.egg-info/requires.txt
pyokt.egg-info/top_level.txt
pyokt/jars/open-korean-text-2.3.1.jar
pyokt/jars/pyokt.jar
pyokt/jars/scala-library-2.12.2.jar
pyokt/jars/twitter-text-1.14.3.jar