Metadata-Version: 1.1
Name: pyokt
Version: 0.1.7
Summary: open-korean-text wrapper for python
Home-page: https://github.com/cookieshake/pyokt
Author: cookieshake
Author-email: cookieshake@github.com
License: UNKNOWN
Keywords: open-korean-text korean text tokenize
Platform: UNKNOWN
Classifier: Development Status :: 4 - Beta
Classifier: Programming Language :: Python :: 3
